README.rst
setup.py
url_summary/__init__.py
url_summary/url_summary.py
url_summary.egg-info/PKG-INFO
url_summary.egg-info/SOURCES.txt
url_summary.egg-info/dependency_links.txt
url_summary.egg-info/requires.txt
url_summary.egg-info/top_level.txt